util/__init__.py
util/os_env.py
util/db/__init__.py
util/db/connections.py
util/log/__init__.py
util/log/logger.py
util/log/sys_logger.py
zhangpan_soft_commons-0.4.4.dist-info/LICENSE
zhangpan_soft_commons-0.4.4.dist-info/METADATA
zhangpan_soft_commons-0.4.4.dist-info/WHEEL
zhangpan_soft_commons-0.4.4.dist-info/top_level.txt
zhangpan_soft_commons-0.4.4.dist-info/RECORD
