Metadata-Version: 2.1
Name: zhangpan-soft-commons
Version: 0.4.4
Summary: my commons
Home-page: https://github.com/zhangpan-soft/py-commons
Author: zhangpan_soft
Author-email: zhangpan_soft@163.com
License: MIT
Classifier: License :: OSI Approved :: MIT License
Classifier: Programming Language :: Python
Classifier: Programming Language :: Python :: 3
Classifier: Programming Language :: Python :: 3.6
Classifier: Programming Language :: Python :: Implementation :: CPython
Classifier: Programming Language :: Python :: Implementation :: PyPy
Requires-Python: >=3.6.0
License-File: LICENSE
